django_model_to_typescript_types/__init__.py
django_model_to_typescript_types/apps.py
django_model_to_typescript_types/modeltotypescriptconverter.py
django_model_to_typescript_types/management/__init__.py
django_model_to_typescript_types/management/commands/__init__.py
django_model_to_typescript_types/management/commands/django2ts.py
django_model_to_typescript_types/migrations/__init__.py
dajngo_models_typescript_types-0.2.dist-info/LICENSE
dajngo_models_typescript_types-0.2.dist-info/METADATA
dajngo_models_typescript_types-0.2.dist-info/WHEEL
dajngo_models_typescript_types-0.2.dist-info/entry_points.txt
dajngo_models_typescript_types-0.2.dist-info/top_level.txt
dajngo_models_typescript_types-0.2.dist-info/RECORD
