Metadata-Version: 2.1
Name: dajngo-models-typescript-types
Version: 0.2
Summary: A package to create your Typescript Types/Models from your Django Models.
Home-page: https://github.com/enzofrnt/Django-Model-to-TypeScript
Author: Enzo_frnt
Classifier: Framework :: Django
Classifier: Programming Language :: Python :: 3
Classifier: License :: OSI Approved :: MIT License
License-File: LICENSE
Requires-Dist: django
